{
  "1385.1": {
    "codec": "O3EComplexType",
    "len": 4,
    "id": "GridEnergy",
    "args": {
      "subTypes": [
        {
          "codec": "O3EFloat32",
          "len": 4,
          "id": "ImportCumulated",
          "args": {
            "scale": 1000.0,
            "offset": 0
          }
        }
      ]
    }
  },
  "1385.2": {
    "codec": "O3EComplexType",
    "len": 4,
    "id": "GridEnergy",
    "args": {
      "subTypes": [
        {
          "codec": "O3EFloat32",
          "len": 4,
          "id": "ExportCumulated",
          "args": {
            "scale": 1000.0,
            "offset": 0
          }
        }
      ]
    }
  },
  "1385.3": {
    "codec": "O3EComplexType",
    "len": 1,
    "id": "GridState",
    "args": {
      "subTypes": [
        {
          "codec": "O3EStateEM",
          "len": 1,
          "id": "OperationState",
          "args": {
            "offset": 0
          }
        }
      ]
    }
  },
  "1385.4": {
    "codec": "O3EComplexType",
    "len": 4,
    "id": "GridActivePower",
    "args": {
      "subTypes": [
        {
          "codec": "O3EInt16",
          "len": 2,
          "id": "Total",
          "args": {
            "scale": 1.0,
            "signed": true,
            "offset": 0
          }
        }
      ]
    }
  },
  "1385.5": {
    "codec": "O3EComplexType",
    "len": 4,
    "id": "Unkown_1385_05",
    "args": {
      "subTypes": [
        {
          "codec": "O3EFloat16",
          "len": 2,
          "id": "Unknown_0",
          "args": {
            "scale": 1.0,
            "offset": 0
          }
        },
        {
          "codec": "O3EFloat16",
          "len": 2,
          "id": "Unknown_1",
          "args": {
            "scale": 1.0,
            "offset": 0
          }
        }
      ]
    }
  },
  "1385.6": {
    "codec": "O3EComplexType",
    "len": 2,
    "id": "GridCurrent",
    "args": {
      "subTypes": [
        {
          "codec": "O3EInt16",
          "len": 2,
          "id": "L1",
          "args": {
            "scale": 1.0,
            "signed": true,
            "offset": 0
          }
        }
      ]
    }
  },
  "1385.7": {
    "codec": "O3EComplexType",
    "len": 4,
    "id": "GridVoltage",
    "args": {
      "subTypes": [
        {
          "codec": "O3EInt32",
          "len": 4,
          "id": "L1",
          "args": {
            "scale": 1.0,
            "signed": false,
            "offset": 0
          }
        }
      ]
    }
  },
  "1385.8": {
    "codec": "O3EComplexType",
    "len": 4,
    "id": "GridActivePower",
    "args": {
      "subTypes": [
        {
          "codec": "O3EInt16",
          "len": 2,
          "id": "L1",
          "args": {
            "scale": 1.0,
            "signed": true,
            "offset": 0
          }
        }
      ]
    }
  },
  "1385.9": {
    "codec": "O3EComplexType",
    "len": 4,
    "id": "GridReactivePower",
    "args": {
      "subTypes": [
        {
          "codec": "O3EInt16",
          "len": 2,
          "id": "L1",
          "args": {
            "scale": 1.0,
            "signed": true,
            "offset": 0
          }
        }
      ]
    }
  },
  "1385.10": {
    "codec": "O3EComplexType",
    "len": 2,
    "id": "GridCurrent",
    "args": {
      "subTypes": [
        {
          "codec": "O3EInt16",
          "len": 2,
          "id": "L2",
          "args": {
            "scale": 1.0,
            "signed": true,
            "offset": 0
          }
        }
      ]
    }
  },
  "1385.11": {
    "codec": "O3EComplexType",
    "len": 4,
    "id": "GridVoltage",
    "args": {
      "subTypes": [
        {
          "codec": "O3EInt32",
          "len": 4,
          "id": "L2",
          "args": {
            "scale": 1.0,
            "signed": false,
            "offset": 0
          }
        }
      ]
    }
  },
  "1385.12": {
    "codec": "O3EComplexType",
    "len": 4,
    "id": "GridActivePower",
    "args": {
      "subTypes": [
        {
          "codec": "O3EInt16",
          "len": 2,
          "id": "L2",
          "args": {
            "scale": 1.0,
            "signed": true,
            "offset": 0
          }
        }
      ]
    }
  },
  "1385.13": {
    "codec": "O3EComplexType",
    "len": 4,
    "id": "GridReactivePower",
    "args": {
      "subTypes": [
        {
          "codec": "O3EInt16",
          "len": 2,
          "id": "L2",
          "args": {
            "scale": 1.0,
            "signed": true,
            "offset": 0
          }
        }
      ]
    }
  },
  "1385.14": {
    "codec": "O3EComplexType",
    "len": 2,
    "id": "GridCurrent",
    "args": {
      "subTypes": [
        {
          "codec": "O3EInt16",
          "len": 2,
          "id": "L3",
          "args": {
            "scale": 1.0,
            "signed": true,
            "offset": 0
          }
        }
      ]
    }
  },
  "1385.15": {
    "codec": "O3EComplexType",
    "len": 4,
    "id": "GridVoltage",
    "args": {
      "subTypes": [
        {
          "codec": "O3EInt32",
          "len": 4,
          "id": "L3",
          "args": {
            "scale": 1.0,
            "signed": false,
            "offset": 0
          }
        }
      ]
    }
  },
  "1385.16": {
    "codec": "O3EComplexType",
    "len": 4,
    "id": "GridActivePower",
    "args": {
      "subTypes": [
        {
          "codec": "O3EInt16",
          "len": 2,
          "id": "L3",
          "args": {
            "scale": 1.0,
            "signed": true,
            "offset": 0
          }
        }
      ]
    }
  },
  "1385.17": {
    "codec": "O3EComplexType",
    "len": 4,
    "id": "GridReactivePower",
    "args": {
      "subTypes": [
        {
          "codec": "O3EInt16",
          "len": 2,
          "id": "L3",
          "args": {
            "scale": 1.0,
            "signed": true,
            "offset": 0
          }
        }
      ]
    }
  },
  "Version": "20240417"
}